{
  "universe_size": 50,
  "generated_date": "2026-05-13",
  "generated_date_pretty": "Wednesday · 13 May 2026",
  "today": "2026-05-13",
  "today_pretty": "Wednesday · 13 May 2026",
  "signal_date": "2026-05-13",
  "signal_date_pretty": "Wednesday · 13 May 2026",
  "weekly_signal_date": "2026-05-08",
  "weekly_signal_date_pretty": "週始 08 May 2026",
  "run_time": "09:24",
  "freshness": {
    "ok": 300,
    "fail": 0,
    "total": 300,
    "cache_only": 0
  },
  "daily": [
    {
      "code": "3653.TW",
      "raw_code": "3653",
      "market": "TWSE",
      "kind": "daily",
      "name": "健策",
      "date": "2026-05-13",
      "close": 3530.0,
      "pattern": "向下窗口",
      "direction": "賣出",
      "rsi": 36.96,
      "ma_dist": {
        "ma10": -20.14,
        "ma20": -24.65,
        "ma50": -13.54,
        "ma200_d": 27.88,
        "ma200_w": null
      },
      "chart": "charts/3653_TW_daily_20260513.html",
      "chart_daily": "charts/3653_TW_daily_20260513.html",
      "chart_weekly": "charts/3653_TW_weekly_20260508.html",
      "charts": {
        "daily": "charts/3653_TW_daily_20260513.html",
        "weekly": "charts/3653_TW_weekly_20260508.html"
      },
      "chart_focus_dates": {
        "daily": "2026-05-13",
        "weekly": "2026-05-08"
      }
    },
    {
      "code": "1815.TWO",
      "raw_code": "1815",
      "market": "TPEx",
      "kind": "daily",
      "name": "富喬",
      "date": "2026-05-13",
      "close": 105.5,
      "pattern": "向下窗口",
      "direction": "賣出",
      "rsi": 45.6,
      "ma_dist": {
        "ma10": -3.96,
        "ma20": -5.91,
        "ma50": -2.81,
        "ma200_d": 25.73,
        "ma200_w": null
      },
      "chart": "charts/1815_TWO_daily_20260513.html",
      "chart_daily": "charts/1815_TWO_daily_20260513.html",
      "chart_weekly": "charts/1815_TWO_weekly_20260508.html",
      "charts": {
        "daily": "charts/1815_TWO_daily_20260513.html",
        "weekly": "charts/1815_TWO_weekly_20260508.html"
      },
      "chart_focus_dates": {
        "daily": "2026-05-13",
        "weekly": "2026-05-08"
      }
    },
    {
      "code": "3665.TW",
      "raw_code": "3665",
      "market": "TWSE",
      "kind": "daily",
      "name": "貿聯-KY",
      "date": "2026-05-13",
      "close": 2500.0,
      "pattern": "向下窗口",
      "direction": "賣出",
      "rsi": 49.54,
      "ma_dist": {
        "ma10": -10.14,
        "ma20": -5.93,
        "ma50": 16.45,
        "ma200_d": 69.56,
        "ma200_w": null
      },
      "chart": "charts/3665_TW_daily_20260513.html",
      "chart_daily": "charts/3665_TW_daily_20260513.html",
      "chart_weekly": "charts/3665_TW_weekly_20260508.html",
      "charts": {
        "daily": "charts/3665_TW_daily_20260513.html",
        "weekly": "charts/3665_TW_weekly_20260508.html"
      },
      "chart_focus_dates": {
        "daily": "2026-05-13",
        "weekly": "2026-05-08"
      }
    },
    {
      "code": "3260.TWO",
      "raw_code": "3260",
      "market": "TPEx",
      "kind": "daily",
      "name": "威剛",
      "date": "2026-05-13",
      "close": 434.0,
      "pattern": "向下窗口",
      "direction": "賣出",
      "rsi": 53.43,
      "ma_dist": {
        "ma10": -3.3,
        "ma20": 2.36,
        "ma50": 11.4,
        "ma200_d": 83.37,
        "ma200_w": null
      },
      "chart": "charts/3260_TWO_daily_20260513.html",
      "chart_daily": "charts/3260_TWO_daily_20260513.html",
      "chart_weekly": "charts/3260_TWO_weekly_20260508.html",
      "charts": {
        "daily": "charts/3260_TWO_daily_20260513.html",
        "weekly": "charts/3260_TWO_weekly_20260508.html"
      },
      "chart_focus_dates": {
        "daily": "2026-05-13",
        "weekly": "2026-05-08"
      }
    },
    {
      "code": "8046.TW",
      "raw_code": "8046",
      "market": "TWSE",
      "kind": "daily",
      "name": "南電",
      "date": "2026-05-13",
      "close": 880.0,
      "pattern": "向下窗口",
      "direction": "賣出",
      "rsi": 57.54,
      "ma_dist": {
        "ma10": -5.71,
        "ma20": 1.52,
        "ma50": 30.65,
        "ma200_d": 144.14,
        "ma200_w": null
      },
      "chart": "charts/8046_TW_daily_20260513.html",
      "chart_daily": "charts/8046_TW_daily_20260513.html",
      "chart_weekly": "charts/8046_TW_weekly_20260508.html",
      "charts": {
        "daily": "charts/8046_TW_daily_20260513.html",
        "weekly": "charts/8046_TW_weekly_20260508.html"
      },
      "chart_focus_dates": {
        "daily": "2026-05-13",
        "weekly": "2026-05-08"
      }
    },
    {
      "code": "2308.TW",
      "raw_code": "2308",
      "market": "TWSE",
      "kind": "daily",
      "name": "台達電",
      "date": "2026-05-13",
      "close": 2165.0,
      "pattern": "向下窗口",
      "direction": "賣出",
      "rsi": 63.23,
      "ma_dist": {
        "ma10": -1.64,
        "ma20": 4.06,
        "ma50": 26.81,
        "ma200_d": 95.69,
        "ma200_w": null
      },
      "chart": "charts/2308_TW_daily_20260513.html",
      "chart_daily": "charts/2308_TW_daily_20260513.html",
      "chart_weekly": "charts/2308_TW_weekly_20260508.html",
      "charts": {
        "daily": "charts/2308_TW_daily_20260513.html",
        "weekly": "charts/2308_TW_weekly_20260508.html"
      },
      "chart_focus_dates": {
        "daily": "2026-05-13",
        "weekly": "2026-05-08"
      }
    },
    {
      "code": "3661.TW",
      "raw_code": "3661",
      "market": "TWSE",
      "kind": "daily",
      "name": "世芯-KY",
      "date": "2026-05-13",
      "close": 4780.0,
      "pattern": "向下窗口",
      "direction": "賣出",
      "rsi": 63.59,
      "ma_dist": {
        "ma10": 3.34,
        "ma20": 13.16,
        "ma50": 34.94,
        "ma200_d": 35.81,
        "ma200_w": null
      },
      "chart": "charts/3661_TW_daily_20260513.html",
      "chart_daily": "charts/3661_TW_daily_20260513.html",
      "chart_weekly": "charts/3661_TW_weekly_20260508.html",
      "charts": {
        "daily": "charts/3661_TW_daily_20260513.html",
        "weekly": "charts/3661_TW_weekly_20260508.html"
      },
      "chart_focus_dates": {
        "daily": "2026-05-13",
        "weekly": "2026-05-08"
      }
    },
    {
      "code": "2301.TW",
      "raw_code": "2301",
      "market": "TWSE",
      "kind": "daily",
      "name": "光寶科",
      "date": "2026-05-13",
      "close": 211.5,
      "pattern": "向下窗口",
      "direction": "賣出",
      "rsi": 64.55,
      "ma_dist": {
        "ma10": 8.85,
        "ma20": 16.98,
        "ma50": 27.13,
        "ma200_d": 33.59,
        "ma200_w": null
      },
      "chart": "charts/2301_TW_daily_20260513.html",
      "chart_daily": "charts/2301_TW_daily_20260513.html",
      "chart_weekly": "charts/2301_TW_weekly_20260508.html",
      "charts": {
        "daily": "charts/2301_TW_daily_20260513.html",
        "weekly": "charts/2301_TW_weekly_20260508.html"
      },
      "chart_focus_dates": {
        "daily": "2026-05-13",
        "weekly": "2026-05-08"
      }
    },
    {
      "code": "6488.TWO",
      "raw_code": "6488",
      "market": "TPEx",
      "kind": "daily",
      "name": "環球晶",
      "date": "2026-05-13",
      "close": 750.0,
      "pattern": "向下窗口",
      "direction": "賣出",
      "rsi": 64.81,
      "ma_dist": {
        "ma10": 6.02,
        "ma20": 17.77,
        "ma50": 43.09,
        "ma200_d": 68.08,
        "ma200_w": null
      },
      "chart": "charts/6488_TWO_daily_20260513.html",
      "chart_daily": "charts/6488_TWO_daily_20260513.html",
      "chart_weekly": "charts/6488_TWO_weekly_20260508.html",
      "charts": {
        "daily": "charts/6488_TWO_daily_20260513.html",
        "weekly": "charts/6488_TWO_weekly_20260508.html"
      },
      "chart_focus_dates": {
        "daily": "2026-05-13",
        "weekly": "2026-05-08"
      }
    },
    {
      "code": "3443.TW",
      "raw_code": "3443",
      "market": "TWSE",
      "kind": "daily",
      "name": "創意",
      "date": "2026-05-13",
      "close": 5330.0,
      "pattern": "向下窗口",
      "direction": "賣出",
      "rsi": 71.79,
      "ma_dist": {
        "ma10": 6.29,
        "ma20": 22.68,
        "ma50": 66.05,
        "ma200_d": 149.19,
        "ma200_w": null
      },
      "chart": "charts/3443_TW_daily_20260513.html",
      "chart_daily": "charts/3443_TW_daily_20260513.html",
      "chart_weekly": "charts/3443_TW_weekly_20260508.html",
      "charts": {
        "daily": "charts/3443_TW_daily_20260513.html",
        "weekly": "charts/3443_TW_weekly_20260508.html"
      },
      "chart_focus_dates": {
        "daily": "2026-05-13",
        "weekly": "2026-05-08"
      }
    },
    {
      "code": "2454.TW",
      "raw_code": "2454",
      "market": "TWSE",
      "kind": "daily",
      "name": "聯發科",
      "date": "2026-05-13",
      "close": 3495.0,
      "pattern": "向下窗口",
      "direction": "賣出",
      "rsi": 73.76,
      "ma_dist": {
        "ma10": 6.67,
        "ma20": 28.59,
        "ma50": 67.97,
        "ma200_d": 119.93,
        "ma200_w": null
      },
      "chart": "charts/2454_TW_daily_20260513.html",
      "chart_daily": "charts/2454_TW_daily_20260513.html",
      "chart_weekly": "charts/2454_TW_weekly_20260508.html",
      "charts": {
        "daily": "charts/2454_TW_daily_20260513.html",
        "weekly": "charts/2454_TW_weekly_20260508.html"
      },
      "chart_focus_dates": {
        "daily": "2026-05-13",
        "weekly": "2026-05-08"
      }
    },
    {
      "code": "5289.TWO",
      "raw_code": "5289",
      "market": "TPEx",
      "kind": "daily",
      "name": "宜鼎",
      "date": "2026-05-13",
      "close": 1765.0,
      "pattern": "向下窗口",
      "direction": "賣出",
      "rsi": 76.25,
      "ma_dist": {
        "ma10": 15.78,
        "ma20": 33.38,
        "ma50": 56.09,
        "ma200_d": 185.18,
        "ma200_w": null
      },
      "chart": "charts/5289_TWO_daily_20260513.html",
      "chart_daily": "charts/5289_TWO_daily_20260513.html",
      "chart_weekly": "charts/5289_TWO_weekly_20260508.html",
      "charts": {
        "daily": "charts/5289_TWO_daily_20260513.html",
        "weekly": "charts/5289_TWO_weekly_20260508.html"
      },
      "chart_focus_dates": {
        "daily": "2026-05-13",
        "weekly": "2026-05-08"
      }
    }
  ],
  "weekly": [
    {
      "code": "1815.TWO",
      "raw_code": "1815",
      "market": "TPEx",
      "kind": "weekly",
      "name": "富喬",
      "date": "2026-05-08",
      "close": 107.0,
      "pattern": "倒錘子線",
      "direction": "買入",
      "rsi": 45.6,
      "ma_dist": {
        "ma10": -2.59,
        "ma20": -4.57,
        "ma50": -1.43,
        "ma200_d": 27.51,
        "ma200_w": null
      },
      "chart": "charts/1815_TWO_daily_20260513.html",
      "chart_daily": "charts/1815_TWO_daily_20260513.html",
      "chart_weekly": "charts/1815_TWO_weekly_20260508.html",
      "charts": {
        "daily": "charts/1815_TWO_daily_20260513.html",
        "weekly": "charts/1815_TWO_weekly_20260508.html"
      },
      "chart_focus_dates": {
        "daily": "2026-05-13",
        "weekly": "2026-05-08"
      }
    },
    {
      "code": "3711.TW",
      "raw_code": "3711",
      "market": "TWSE",
      "kind": "weekly",
      "name": "日月光投控",
      "date": "2026-05-08",
      "close": 516.0,
      "pattern": "看漲孕線",
      "direction": "買入",
      "rsi": 70.47,
      "ma_dist": {
        "ma10": -1.37,
        "ma20": 4.03,
        "ma50": 25.42,
        "ma200_d": 95.55,
        "ma200_w": null
      },
      "chart": "charts/3711_TW_daily_20260513.html",
      "chart_daily": "charts/3711_TW_daily_20260513.html",
      "chart_weekly": "charts/3711_TW_weekly_20260508.html",
      "charts": {
        "daily": "charts/3711_TW_daily_20260513.html",
        "weekly": "charts/3711_TW_weekly_20260508.html"
      },
      "chart_focus_dates": {
        "daily": "2026-05-13",
        "weekly": "2026-05-08"
      }
    },
    {
      "code": "3443.TW",
      "raw_code": "3443",
      "market": "TWSE",
      "kind": "weekly",
      "name": "創意",
      "date": "2026-05-08",
      "close": 5210.0,
      "pattern": "向上窗口",
      "direction": "買入",
      "rsi": 71.79,
      "ma_dist": {
        "ma10": 3.9,
        "ma20": 19.91,
        "ma50": 62.31,
        "ma200_d": 143.58,
        "ma200_w": null
      },
      "chart": "charts/3443_TW_daily_20260513.html",
      "chart_daily": "charts/3443_TW_daily_20260513.html",
      "chart_weekly": "charts/3443_TW_weekly_20260508.html",
      "charts": {
        "daily": "charts/3443_TW_daily_20260513.html",
        "weekly": "charts/3443_TW_weekly_20260508.html"
      },
      "chart_focus_dates": {
        "daily": "2026-05-13",
        "weekly": "2026-05-08"
      }
    },
    {
      "code": "2454.TW",
      "raw_code": "2454",
      "market": "TWSE",
      "kind": "weekly",
      "name": "聯發科",
      "date": "2026-05-08",
      "close": 3630.0,
      "pattern": "向上窗口",
      "direction": "買入",
      "rsi": 73.76,
      "ma_dist": {
        "ma10": 10.79,
        "ma20": 33.55,
        "ma50": 74.46,
        "ma200_d": 128.42,
        "ma200_w": null
      },
      "chart": "charts/2454_TW_daily_20260513.html",
      "chart_daily": "charts/2454_TW_daily_20260513.html",
      "chart_weekly": "charts/2454_TW_weekly_20260508.html",
      "charts": {
        "daily": "charts/2454_TW_daily_20260513.html",
        "weekly": "charts/2454_TW_weekly_20260508.html"
      },
      "chart_focus_dates": {
        "daily": "2026-05-13",
        "weekly": "2026-05-08"
      }
    },
    {
      "code": "3653.TW",
      "raw_code": "3653",
      "market": "TWSE",
      "kind": "weekly",
      "name": "健策",
      "date": "2026-05-08",
      "close": 3650.0,
      "pattern": "大陰線",
      "direction": "賣出",
      "rsi": 36.96,
      "ma_dist": {
        "ma10": -17.42,
        "ma20": -22.08,
        "ma50": -10.6,
        "ma200_d": 32.23,
        "ma200_w": null
      },
      "chart": "charts/3653_TW_daily_20260513.html",
      "chart_daily": "charts/3653_TW_daily_20260513.html",
      "chart_weekly": "charts/3653_TW_weekly_20260508.html",
      "charts": {
        "daily": "charts/3653_TW_daily_20260513.html",
        "weekly": "charts/3653_TW_weekly_20260508.html"
      },
      "chart_focus_dates": {
        "daily": "2026-05-13",
        "weekly": "2026-05-08"
      }
    },
    {
      "code": "1303.TW",
      "raw_code": "1303",
      "market": "TWSE",
      "kind": "weekly",
      "name": "南亞",
      "date": "2026-05-08",
      "close": 88.6,
      "pattern": "流星線",
      "direction": "賣出",
      "rsi": 48.65,
      "ma_dist": {
        "ma10": -1.93,
        "ma20": -0.56,
        "ma50": 5.26,
        "ma200_d": 48.84,
        "ma200_w": null
      },
      "chart": "charts/1303_TW_daily_20260513.html",
      "chart_daily": "charts/1303_TW_daily_20260513.html",
      "chart_weekly": "charts/1303_TW_weekly_20260508.html",
      "charts": {
        "daily": "charts/1303_TW_daily_20260513.html",
        "weekly": "charts/1303_TW_weekly_20260508.html"
      },
      "chart_focus_dates": {
        "daily": "2026-05-13",
        "weekly": "2026-05-08"
      }
    },
    {
      "code": "8046.TW",
      "raw_code": "8046",
      "market": "TWSE",
      "kind": "weekly",
      "name": "南電",
      "date": "2026-05-08",
      "close": 854.0,
      "pattern": "大陰線",
      "direction": "賣出",
      "rsi": 57.54,
      "ma_dist": {
        "ma10": -8.5,
        "ma20": -1.48,
        "ma50": 26.79,
        "ma200_d": 136.93,
        "ma200_w": null
      },
      "chart": "charts/8046_TW_daily_20260513.html",
      "chart_daily": "charts/8046_TW_daily_20260513.html",
      "chart_weekly": "charts/8046_TW_weekly_20260508.html",
      "charts": {
        "daily": "charts/8046_TW_daily_20260513.html",
        "weekly": "charts/8046_TW_weekly_20260508.html"
      },
      "chart_focus_dates": {
        "daily": "2026-05-13",
        "weekly": "2026-05-08"
      }
    },
    {
      "code": "8046.TW",
      "raw_code": "8046",
      "market": "TWSE",
      "kind": "weekly",
      "name": "南電",
      "date": "2026-05-08",
      "close": 854.0,
      "pattern": "看跌吞沒",
      "direction": "賣出",
      "rsi": 57.54,
      "ma_dist": {
        "ma10": -8.5,
        "ma20": -1.48,
        "ma50": 26.79,
        "ma200_d": 136.93,
        "ma200_w": null
      },
      "chart": "charts/8046_TW_daily_20260513.html",
      "chart_daily": "charts/8046_TW_daily_20260513.html",
      "chart_weekly": "charts/8046_TW_weekly_20260508.html",
      "charts": {
        "daily": "charts/8046_TW_daily_20260513.html",
        "weekly": "charts/8046_TW_weekly_20260508.html"
      },
      "chart_focus_dates": {
        "daily": "2026-05-13",
        "weekly": "2026-05-08"
      }
    },
    {
      "code": "2337.TW",
      "raw_code": "2337",
      "market": "TWSE",
      "kind": "weekly",
      "name": "旺宏",
      "date": "2026-05-08",
      "close": 153.0,
      "pattern": "流星線",
      "direction": "賣出",
      "rsi": 59.14,
      "ma_dist": {
        "ma10": -4.73,
        "ma20": 3.1,
        "ma50": 13.27,
        "ma200_d": 143.35,
        "ma200_w": null
      },
      "chart": "charts/2337_TW_daily_20260513.html",
      "chart_daily": "charts/2337_TW_daily_20260513.html",
      "chart_weekly": "charts/2337_TW_weekly_20260508.html",
      "charts": {
        "daily": "charts/2337_TW_daily_20260513.html",
        "weekly": "charts/2337_TW_weekly_20260508.html"
      },
      "chart_focus_dates": {
        "daily": "2026-05-13",
        "weekly": "2026-05-08"
      }
    },
    {
      "code": "3037.TW",
      "raw_code": "3037",
      "market": "TWSE",
      "kind": "weekly",
      "name": "欣興",
      "date": "2026-05-08",
      "close": 818.0,
      "pattern": "看跌吞沒",
      "direction": "賣出",
      "rsi": 66.27,
      "ma_dist": {
        "ma10": -5.98,
        "ma20": 2.94,
        "ma50": 30.69,
        "ma200_d": 168.13,
        "ma200_w": null
      },
      "chart": "charts/3037_TW_daily_20260513.html",
      "chart_daily": "charts/3037_TW_daily_20260513.html",
      "chart_weekly": "charts/3037_TW_weekly_20260508.html",
      "charts": {
        "daily": "charts/3037_TW_daily_20260513.html",
        "weekly": "charts/3037_TW_weekly_20260508.html"
      },
      "chart_focus_dates": {
        "daily": "2026-05-13",
        "weekly": "2026-05-08"
      }
    },
    {
      "code": "2383.TW",
      "raw_code": "2383",
      "market": "TWSE",
      "kind": "weekly",
      "name": "台光電",
      "date": "2026-05-08",
      "close": 4750.0,
      "pattern": "流星線",
      "direction": "賣出",
      "rsi": 72.57,
      "ma_dist": {
        "ma10": -0.65,
        "ma20": 6.98,
        "ma50": 38.69,
        "ma200_d": 148.69,
        "ma200_w": null
      },
      "chart": "charts/2383_TW_daily_20260513.html",
      "chart_daily": "charts/2383_TW_daily_20260513.html",
      "chart_weekly": "charts/2383_TW_weekly_20260508.html",
      "charts": {
        "daily": "charts/2383_TW_daily_20260513.html",
        "weekly": "charts/2383_TW_weekly_20260508.html"
      },
      "chart_focus_dates": {
        "daily": "2026-05-13",
        "weekly": "2026-05-08"
      }
    }
  ]
}